sosi_api/__init__.py
sosi_api/__main__.py
sosi_api/client.py
sosi_api/exceptions.py
sosi_api/utils/__init__.py
sosi_api/utils/dt.py
sosi_api/utils/signatures.py
sosi_api/utils/status_handlers.py
tests/__init__.py
sosi_api-0.1.4.dist-info/METADATA
sosi_api-0.1.4.dist-info/WHEEL
sosi_api-0.1.4.dist-info/top_level.txt
sosi_api-0.1.4.dist-info/RECORD
